tests/test_str_utils.py
tests/__init__.py
tests/app_handlers.py
tests/test_handler.py
torskel/torskel_ping_handler.py
torskel/__init__.py
torskel/torskel_app.py
torskel/torskel_handler.py
torskel/torskel_secured_handler.py
torskel/str_utils.py
torskel/torskel_mixins/__init__.py
torskel/torskel_mixins/log_mix.py
torskel/torskel_mixins/redis_mixin.py
torskel/libs/__init__.py
torskel/libs/str_consts.py
torskel/libs/event_controller.py
torskel/libs/startup.py
torskel/libs/db_utils/__init__.py
torskel/libs/db_utils/mongo.py
torskel/libs/auth/__init__.py
torskel/libs/auth/jwt.py
torskel-0.7.4.dist-info/top_level.txt
torskel-0.7.4.dist-info/METADATA
torskel-0.7.4.dist-info/WHEEL
torskel-0.7.4.dist-info/DESCRIPTION.rst
torskel-0.7.4.dist-info/RECORD
torskel-0.7.4.dist-info/metadata.json
